{
	"crops": "Crops",
	"ores": "Ores",
	"dimensions": "Dimensions",
	"storage": "Storage",
	"transfer": "Transfer",
	"generators": "Generators",
	"machines": "Machines",
	"mills": "Mills",
	"redstone": "Redstone",
	"glass": "Glass",
	"decorative": "Decorative",
	"angel_block.mdx": "Angel Block",
	"blackout_curtain.mdx": "Blackout Curtain",
	"chandelier.mdx": "Chandelier",
	"compressed_blocks.mdx": "Compressed Blocks",
	"conveyor_belt.mdx": "Conveyor Belt",
	"creative_harvest.mdx": "Creative Harvest",
	"cursed_earth.mdx": "Cursed Earth",
	"ender_core.mdx": "Ender Core",
	"ender_porcupine.mdx": "Ender Porcupine",
	"ender_quarry_upgrades": "Ender Quarry Upgrades",
	"magical_snow_globe.mdx": "Magical Snow Globe",
	"magical_wood.mdx": "Magical Wood",
	"magnum_torch.mdx": "Magnum Torch",
	"moon_stone_ore.mdx": "Moon Stone Ore",
	"peaceful_table.mdx": "Peaceful Table",
	"resturbed_mob_spawner.mdx": "Resturbed Mob Spawner",
	"sound_muffler.mdx": "Sound Muffler"
}
